{"name":"Test","id":-94183297596851864162352591929519166995,"left_keys":[{"time":1797,"holding":0},{"time":1857,"holding":0},{"time":2109,"holding":0},{"time":2151,"holding":291},{"time":2529,"holding":0},{"time":2571,"holding":0},{"time":2865,"holding":0},{"time":2907,"holding":0},{"time":3201,"holding":0},{"time":3243,"holding":0},{"time":3705,"holding":52},{"time":4041,"holding":0},{"time":4234,"holding":0},{"time":4323,"holding":0},{"time":4410,"holding":0},{"time":4493,"holding":0},{"time":4573,"holding":0},{"time":4658,"holding":0},{"time":4741,"holding":0},{"time":4826,"holding":70},{"time":4913,"holding":0},{"time":5028,"holding":165},{"time":5207,"holding":0},{"time":5254,"holding":0},{"time":5423,"holding":0},{"time":5507,"holding":0},{"time":5550,"holding":0},{"time":5596,"holding":0},{"time":5764,"holding":0},{"time":5846,"holding":0},{"time":5886,"holding":0},{"time":5932,"holding":0},{"time":6106,"holding":0},{"time":6190,"holding":0},{"time":6233,"holding":0},{"time":6275,"holding":0},{"time":6443,"holding":0},{"time":6528,"holding":0},{"time":6568,"holding":0},{"time":6612,"holding":0},{"time":6782,"holding":0},{"time":6866,"holding":0},{"time":6907,"holding":0},{"time":6950,"holding":0},{"time":7075,"holding":0},{"time":7120,"holding":0},{"time":7247,"holding":0},{"time":7286,"holding":0},{"time":7457,"holding":0},{"time":7537,"holding":0},{"time":7581,"holding":0},{"time":7623,"holding":0},{"time":7796,"holding":0},{"time":7882,"holding":0},{"time":7923,"holding":0},{"time":7965,"holding":0},{"time":8097,"holding":0},{"time":8182,"holding":0},{"time":8263,"holding":0},{"time":8306,"holding":0},{"time":8522,"holding":0},{"time":8602,"holding":0},{"time":8644,"holding":0},{"time":8733,"holding":0},{"time":8775,"holding":0},{"time":8901,"holding":0},{"time":8945,"holding":0},{"time":8988,"holding":0},{"time":9155,"holding":0},{"time":9239,"holding":0},{"time":9284,"holding":0},{"time":9367,"holding":0},{"time":9447,"holding":0},{"time":9533,"holding":0},{"time":9762,"holding":0},{"time":9782,"holding":0},{"time":9845,"holding":0},{"time":9867,"holding":0},{"time":9992,"holding":0},{"time":10079,"holding":0},{"time":10167,"holding":0},{"time":10247,"holding":0},{"time":10332,"holding":0},{"time":10418,"holding":0},{"time":10455,"holding":133},{"time":10623,"holding":0},{"time":10674,"holding":0},{"time":10965,"holding":0},{"time":11047,"holding":0},{"time":11174,"holding":0},{"time":11344,"holding":0},{"time":11432,"holding":0},{"time":11473,"holding":0},{"time":11521,"holding":0},{"time":11693,"holding":0},{"time":11780,"holding":0},{"time":11818,"holding":0},{"time":11863,"holding":0},{"time":12035,"holding":0},{"time":12121,"holding":0},{"time":12159,"holding":0},{"time":12207,"holding":0},{"time":12376,"holding":0},{"time":12462,"holding":0},{"time":12507,"holding":0},{"time":12549,"holding":0},{"time":12714,"holding":0},{"time":12796,"holding":0},{"time":12835,"holding":0},{"time":12885,"holding":0},{"time":13009,"holding":0},{"time":13224,"holding":0},{"time":13390,"holding":0},{"time":13473,"holding":0},{"time":13516,"holding":0},{"time":13560,"holding":0},{"time":13728,"holding":0},{"time":13810,"holding":0},{"time":13856,"holding":0},{"time":13899,"holding":0},{"time":14025,"holding":0},{"time":14154,"holding":0},{"time":14239,"holding":0},{"time":14448,"holding":0},{"time":14531,"holding":0},{"time":14576,"holding":0},{"time":14615,"holding":0},{"time":14663,"holding":0},{"time":14704,"holding":0},{"time":14745,"holding":0},{"time":14873,"holding":0},{"time":14914,"holding":0},{"time":15214,"holding":0},{"time":15257,"holding":0},{"time":15343,"holding":0},{"time":15462,"holding":0},{"time":15548,"holding":0},{"time":15607,"holding":0},{"time":15633,"holding":0},{"time":15693,"holding":0},{"time":15717,"holding":0},{"time":15778,"holding":0},{"time":15803,"holding":0},{"time":16044,"holding":0},{"time":16392,"holding":0},{"time":16487,"holding":0},{"time":16738,"holding":0},{"time":17015,"holding":0},{"time":17131,"holding":0},{"time":17264,"holding":0},{"time":17490,"holding":0},{"time":17716,"holding":0},{"time":17803,"holding":0},{"time":17890,"holding":0},{"time":18061,"holding":0},{"time":18267,"holding":106},{"time":18594,"holding":0},{"time":18638,"holding":0},{"time":18679,"holding":0},{"time":18723,"holding":0},{"time":18768,"holding":0},{"time":18806,"holding":0},{"time":18848,"holding":0},{"time":18893,"holding":0},{"time":19017,"holding":0},{"time":19185,"holding":0},{"time":19423,"holding":0},{"time":19443,"holding":0},{"time":19660,"holding":0},{"time":19697,"holding":0},{"time":19743,"holding":0},{"time":19762,"holding":0},{"time":19782,"holding":0},{"time":19801,"holding":0},{"time":19902,"holding":0},{"time":20673,"holding":0},{"time":20838,"holding":0},{"time":20921,"holding":0},{"time":20962,"holding":0},{"time":20982,"holding":0},{"time":21001,"holding":0},{"time":21038,"holding":0},{"time":21080,"holding":0},{"time":21100,"holding":0},{"time":21119,"holding":0},{"time":21482,"holding":0},{"time":21516,"holding":0},{"time":21539,"holding":0},{"time":21718,"holding":0},{"time":22000,"holding":0},{"time":22084,"holding":0},{"time":22190,"holding":0},{"time":22209,"holding":0},{"time":22394,"holding":0},{"time":22440,"holding":0},{"time":22479,"holding":0},{"time":22502,"holding":0},{"time":22522,"holding":0},{"time":22817,"holding":0},{"time":22838,"holding":0},{"time":22993,"holding":0},{"time":23151,"holding":0},{"time":23460,"holding":0},{"time":23893,"holding":0},{"time":23916,"holding":0},{"time":24055,"holding":0},{"time":24282,"holding":0},{"time":24319,"holding":0},{"time":24341,"holding":0},{"time":24381,"holding":0},{"time":24551,"holding":0},{"time":24719,"holding":0},{"time":24758,"holding":0},{"time":24800,"holding":0},{"time":24846,"holding":0},{"time":24886,"holding":0},{"time":24930,"holding":0},{"time":24969,"holding":0},{"time":25012,"holding":0},{"time":25055,"holding":0},{"time":25219,"holding":0},{"time":25335,"holding":0},{"time":25540,"holding":0},{"time":25569,"holding":0},{"time":26057,"holding":87},{"time":26757,"holding":0},{"time":26800,"holding":0},{"time":26932,"holding":169},{"time":27444,"holding":87},{"time":28056,"holding":0},{"time":28087,"holding":0},{"time":28406,"holding":0},{"time":28433,"holding":0},{"time":28609,"holding":0},{"time":28901,"holding":0},{"time":29069,"holding":0},{"time":29246,"holding":0},{"time":29432,"holding":0},{"time":29824,"holding":0},{"time":29862,"holding":0},{"time":30014,"holding":0},{"time":30177,"holding":0},{"time":30326,"holding":81},{"time":30492,"holding":69},{"time":30649,"holding":63},{"time":31157,"holding":127},{"time":31500,"holding":125},{"time":31681,"holding":150},{"time":31851,"holding":0},{"time":31894,"holding":0},{"time":32015,"holding":0},{"time":32064,"holding":0},{"time":32199,"holding":0},{"time":32240,"holding":0},{"time":32366,"holding":223},{"time":32956,"holding":0},{"time":33006,"holding":0},{"time":33319,"holding":0},{"time":33347,"holding":0},{"time":33613,"holding":0},{"time":33639,"holding":0},{"time":33897,"holding":0},{"time":33932,"holding":0},{"time":34233,"holding":0},{"time":34285,"holding":0},{"time":34401,"holding":0},{"time":34449,"holding":85},{"time":34826,"holding":0},{"time":34958,"holding":0},{"time":35056,"holding":566}],"up_keys":[{"time":1797,"holding":0},{"time":1899,"holding":0},{"time":2067,"holding":0},{"time":2155,"holding":287},{"time":2529,"holding":0},{"time":2613,"holding":0},{"time":2781,"holding":0},{"time":2865,"holding":0},{"time":2949,"holding":0},{"time":2991,"holding":0},{"time":3076,"holding":0},{"time":3285,"holding":0},{"time":3327,"holding":0},{"time":3537,"holding":55},{"time":3621,"holding":50},{"time":3789,"holding":0},{"time":3873,"holding":50},{"time":3957,"holding":0},{"time":4101,"holding":87},{"time":4532,"holding":0},{"time":4616,"holding":0},{"time":4700,"holding":0},{"time":4784,"holding":0},{"time":4953,"holding":0},{"time":5029,"holding":166},{"time":5207,"holding":0},{"time":5297,"holding":0},{"time":5550,"holding":0},{"time":5636,"holding":0},{"time":5886,"holding":0},{"time":5972,"holding":0},{"time":6233,"holding":0},{"time":6319,"holding":0},{"time":6569,"holding":0},{"time":6656,"holding":0},{"time":6907,"holding":0},{"time":6993,"holding":0},{"time":7075,"holding":0},{"time":7246,"holding":0},{"time":7329,"holding":0},{"time":7581,"holding":0},{"time":7668,"holding":0},{"time":7923,"holding":0},{"time":8009,"holding":0},{"time":8223,"holding":0},{"time":8262,"holding":0},{"time":8346,"holding":0},{"time":8436,"holding":0},{"time":8602,"holding":0},{"time":8688,"holding":0},{"time":8818,"holding":0},{"time":8859,"holding":0},{"time":8944,"holding":0},{"time":9032,"holding":0},{"time":9284,"holding":0},{"time":9367,"holding":0},{"time":9409,"holding":0},{"time":9620,"holding":0},{"time":9680,"holding":0},{"time":9700,"holding":0},{"time":9845,"holding":0},{"time":9867,"holding":0},{"time":10291,"holding":0},{"time":10373,"holding":0},{"time":10456,"holding":133},{"time":10622,"holding":0},{"time":10715,"holding":0},{"time":10882,"holding":0},{"time":11130,"holding":0},{"time":11216,"holding":69},{"time":11472,"holding":0},{"time":11564,"holding":0},{"time":11818,"holding":0},{"time":11908,"holding":0},{"time":12159,"holding":0},{"time":12249,"holding":0},{"time":12507,"holding":0},{"time":12590,"holding":0},{"time":12835,"holding":0},{"time":12927,"holding":0},{"time":13055,"holding":0},{"time":13179,"holding":0},{"time":13265,"holding":0},{"time":13516,"holding":0},{"time":13604,"holding":0},{"time":13856,"holding":0},{"time":13942,"holding":0},{"time":14196,"holding":0},{"time":14277,"holding":0},{"time":14368,"holding":0},{"time":14530,"holding":0},{"time":14787,"holding":0},{"time":14961,"holding":0},{"time":15090,"holding":0},{"time":15175,"holding":0},{"time":15214,"holding":0},{"time":15268,"holding":0},{"time":15301,"holding":0},{"time":15378,"holding":0},{"time":15548,"holding":0},{"time":15607,"holding":0},{"time":15633,"holding":0},{"time":15693,"holding":0},{"time":15717,"holding":0},{"time":15778,"holding":0},{"time":15803,"holding":0},{"time":15885,"holding":90},{"time":16187,"holding":0},{"time":16439,"holding":0},{"time":16525,"holding":0},{"time":16761,"holding":0},{"time":16794,"holding":0},{"time":16962,"holding":0},{"time":16975,"holding":0},{"time":17041,"holding":0},{"time":17107,"holding":0},{"time":17300,"holding":0},{"time":17331,"holding":0},{"time":17359,"holding":0},{"time":17379,"holding":0},{"time":17463,"holding":0},{"time":17516,"holding":0},{"time":18082,"holding":0},{"time":18588,"holding":0},{"time":18637,"holding":0},{"time":18679,"holding":0},{"time":18723,"holding":0},{"time":18768,"holding":0},{"time":18806,"holding":0},{"time":18848,"holding":0},{"time":18893,"holding":0},{"time":18935,"holding":0},{"time":18976,"holding":0},{"time":18996,"holding":0},{"time":19059,"holding":0},{"time":19099,"holding":0},{"time":19141,"holding":0},{"time":19165,"holding":0},{"time":19222,"holding":0},{"time":19242,"holding":0},{"time":19263,"holding":0},{"time":19303,"holding":0},{"time":19324,"holding":0},{"time":19346,"holding":0},{"time":19383,"holding":0},{"time":19402,"holding":0},{"time":19462,"holding":0},{"time":19501,"holding":0},{"time":19540,"holding":0},{"time":19579,"holding":0},{"time":19600,"holding":0},{"time":19620,"holding":0},{"time":19640,"holding":0},{"time":19742,"holding":0},{"time":19763,"holding":0},{"time":19782,"holding":0},{"time":19801,"holding":0},{"time":19822,"holding":0},{"time":19860,"holding":0},{"time":19900,"holding":0},{"time":20256,"holding":0},{"time":20274,"holding":0},{"time":20344,"holding":0},{"time":20586,"holding":0},{"time":20631,"holding":0},{"time":20713,"holding":0},{"time":20751,"holding":0},{"time":20794,"holding":0},{"time":20875,"holding":0},{"time":20962,"holding":0},{"time":20981,"holding":0},{"time":21001,"holding":0},{"time":21038,"holding":0},{"time":21159,"holding":0},{"time":21179,"holding":0},{"time":21199,"holding":0},{"time":21300,"holding":0},{"time":21379,"holding":0},{"time":21456,"holding":0},{"time":21564,"holding":0},{"time":21603,"holding":0},{"time":21641,"holding":0},{"time":21679,"holding":0},{"time":21757,"holding":0},{"time":21963,"holding":0},{"time":22042,"holding":0},{"time":22122,"holding":53},{"time":22226,"holding":0},{"time":22539,"holding":0},{"time":22715,"holding":0},{"time":22855,"holding":0},{"time":23014,"holding":0},{"time":23172,"holding":0},{"time":23503,"holding":0},{"time":23581,"holding":0},{"time":23662,"holding":0},{"time":23939,"holding":0},{"time":24016,"holding":0},{"time":24095,"holding":0},{"time":24150,"holding":0},{"time":24174,"holding":0},{"time":24219,"holding":0},{"time":24340,"holding":0},{"time":24382,"holding":0},{"time":24510,"holding":0},{"time":24679,"holding":0},{"time":24930,"holding":0},{"time":24968,"holding":0},{"time":25012,"holding":0},{"time":25055,"holding":0},{"time":25158,"holding":0},{"time":25189,"holding":0},{"time":25235,"holding":0},{"time":25305,"holding":0},{"time":25366,"holding":0},{"time":25511,"holding":0},{"time":25587,"holding":0},{"time":25714,"holding":0},{"time":25800,"holding":0},{"time":25842,"holding":0},{"time":25886,"holding":0},{"time":25927,"holding":0},{"time":25972,"holding":0},{"time":26018,"holding":0},{"time":26103,"holding":0},{"time":26149,"holding":0},{"time":26194,"holding":0},{"time":26237,"holding":0},{"time":26298,"holding":0},{"time":26323,"holding":0},{"time":26407,"holding":0},{"time":26496,"holding":0},{"time":26585,"holding":0},{"time":26674,"holding":0},{"time":26721,"holding":0},{"time":27101,"holding":154},{"time":27271,"holding":177},{"time":27529,"holding":0},{"time":27557,"holding":0},{"time":27604,"holding":0},{"time":27705,"holding":94},{"time":27883,"holding":95},{"time":28028,"holding":0},{"time":28102,"holding":0},{"time":28173,"holding":0},{"time":28233,"holding":0},{"time":28380,"holding":0},{"time":28452,"holding":0},{"time":28581,"holding":0},{"time":28624,"holding":0},{"time":28665,"holding":0},{"time":28725,"holding":0},{"time":28783,"holding":0},{"time":28873,"holding":0},{"time":28928,"holding":0},{"time":28972,"holding":0},{"time":29097,"holding":0},{"time":29141,"holding":0},{"time":29217,"holding":0},{"time":29276,"holding":0},{"time":29302,"holding":0},{"time":29334,"holding":0},{"time":29401,"holding":0},{"time":29466,"holding":0},{"time":29500,"holding":0},{"time":29534,"holding":0},{"time":29595,"holding":0},{"time":29657,"holding":0},{"time":29712,"holding":0},{"time":29843,"holding":0},{"time":29880,"holding":0},{"time":30034,"holding":0},{"time":30197,"holding":0},{"time":30708,"holding":0},{"time":30897,"holding":0},{"time":30941,"holding":0},{"time":31284,"holding":0},{"time":31623,"holding":0},{"time":31938,"holding":0},{"time":32015,"holding":0},{"time":32110,"holding":0},{"time":32198,"holding":0},{"time":32281,"holding":0},{"time":32366,"holding":216},{"time":32598,"holding":359},{"time":33041,"holding":0},{"time":33278,"holding":0},{"time":33380,"holding":0},{"time":33571,"holding":0},{"time":33668,"holding":0},{"time":33857,"holding":0},{"time":33968,"holding":0},{"time":34141,"holding":0},{"time":34188,"holding":0},{"time":34338,"holding":0},{"time":34732,"holding":0},{"time":35064,"holding":557}],"bottom_keys":[{"time":1797,"holding":0},{"time":1941,"holding":0},{"time":2025,"holding":0},{"time":2158,"holding":284},{"time":2529,"holding":0},{"time":2655,"holding":0},{"time":2697,"holding":0},{"time":2865,"holding":0},{"time":2949,"holding":0},{"time":3201,"holding":0},{"time":3621,"holding":0},{"time":3705,"holding":0},{"time":3789,"holding":0},{"time":3957,"holding":0},{"time":4041,"holding":0},{"time":4100,"holding":93},{"time":4364,"holding":0},{"time":4450,"holding":0},{"time":4990,"holding":0},{"time":5032,"holding":163},{"time":5207,"holding":0},{"time":5337,"holding":0},{"time":5463,"holding":0},{"time":5550,"holding":0},{"time":5680,"holding":0},{"time":5803,"holding":0},{"time":5887,"holding":0},{"time":6018,"holding":0},{"time":6150,"holding":0},{"time":6233,"holding":0},{"time":6361,"holding":0},{"time":6486,"holding":0},{"time":6569,"holding":0},{"time":6695,"holding":0},{"time":6824,"holding":0},{"time":6907,"holding":0},{"time":7032,"holding":0},{"time":7076,"holding":0},{"time":7164,"holding":0},{"time":7247,"holding":0},{"time":7370,"holding":0},{"time":7498,"holding":0},{"time":7583,"holding":0},{"time":7710,"holding":0},{"time":7839,"holding":0},{"time":7923,"holding":0},{"time":8137,"holding":0},{"time":8266,"holding":0},{"time":8478,"holding":0},{"time":8563,"holding":0},{"time":8602,"holding":0},{"time":8690,"holding":0},{"time":8860,"holding":0},{"time":9073,"holding":0},{"time":9198,"holding":0},{"time":9284,"holding":0},{"time":9326,"holding":0},{"time":9363,"holding":0},{"time":9409,"holding":0},{"time":9447,"holding":0},{"time":9534,"holding":0},{"time":9619,"holding":0},{"time":9681,"holding":0},{"time":9701,"holding":0},{"time":9846,"holding":0},{"time":9867,"holding":0},{"time":10121,"holding":0},{"time":10205,"holding":0},{"time":10459,"holding":133},{"time":10623,"holding":0},{"time":10754,"holding":0},{"time":10797,"holding":0},{"time":11263,"holding":0},{"time":11386,"holding":0},{"time":11473,"holding":0},{"time":11605,"holding":0},{"time":11732,"holding":0},{"time":11818,"holding":0},{"time":11951,"holding":0},{"time":12079,"holding":0},{"time":12161,"holding":0},{"time":12293,"holding":0},{"time":12419,"holding":0},{"time":12507,"holding":0},{"time":12631,"holding":0},{"time":12756,"holding":0},{"time":12838,"holding":0},{"time":12967,"holding":0},{"time":13096,"holding":0},{"time":13307,"holding":0},{"time":13431,"holding":0},{"time":13516,"holding":0},{"time":13644,"holding":0},{"time":13772,"holding":0},{"time":13858,"holding":0},{"time":14110,"holding":0},{"time":14407,"holding":0},{"time":14493,"holding":0},{"time":14530,"holding":0},{"time":14788,"holding":0},{"time":14873,"holding":0},{"time":15005,"holding":0},{"time":15131,"holding":0},{"time":15214,"holding":0},{"time":15343,"holding":0},{"time":15380,"holding":0},{"time":15548,"holding":0},{"time":15610,"holding":0},{"time":15632,"holding":0},{"time":15694,"holding":0},{"time":15717,"holding":0},{"time":15781,"holding":0},{"time":15803,"holding":0},{"time":15885,"holding":87},{"time":16035,"holding":0},{"time":16242,"holding":0},{"time":16544,"holding":0},{"time":16777,"holding":0},{"time":16949,"holding":0},{"time":16970,"holding":0},{"time":16987,"holding":0},{"time":17003,"holding":0},{"time":17028,"holding":0},{"time":17083,"holding":0},{"time":17100,"holding":0},{"time":17122,"holding":0},{"time":17142,"holding":0},{"time":17316,"holding":0},{"time":17342,"holding":0},{"time":17451,"holding":0},{"time":17477,"holding":0},{"time":17501,"holding":0},{"time":17530,"holding":0},{"time":17759,"holding":0},{"time":17845,"holding":0},{"time":18102,"holding":87},{"time":18513,"holding":0},{"time":18588,"holding":0},{"time":18637,"holding":0},{"time":18680,"holding":0},{"time":18723,"holding":0},{"time":18768,"holding":0},{"time":18806,"holding":0},{"time":18848,"holding":0},{"time":18891,"holding":0},{"time":18976,"holding":0},{"time":18998,"holding":0},{"time":19017,"holding":0},{"time":19058,"holding":0},{"time":19144,"holding":0},{"time":19165,"holding":0},{"time":19183,"holding":0},{"time":19222,"holding":0},{"time":19243,"holding":0},{"time":19306,"holding":0},{"time":19325,"holding":0},{"time":19381,"holding":0},{"time":19400,"holding":0},{"time":19420,"holding":0},{"time":19440,"holding":0},{"time":19460,"holding":0},{"time":19541,"holding":0},{"time":19579,"holding":0},{"time":19601,"holding":0},{"time":19620,"holding":0},{"time":19638,"holding":0},{"time":19744,"holding":0},{"time":19763,"holding":0},{"time":19780,"holding":0},{"time":19800,"holding":0},{"time":19823,"holding":0},{"time":19860,"holding":0},{"time":19900,"holding":0},{"time":20292,"holding":0},{"time":20326,"holding":0},{"time":20366,"holding":0},{"time":20633,"holding":0},{"time":20675,"holding":0},{"time":20715,"holding":0},{"time":20798,"holding":0},{"time":20839,"holding":0},{"time":20877,"holding":0},{"time":20963,"holding":0},{"time":20983,"holding":0},{"time":21000,"holding":0},{"time":21039,"holding":0},{"time":21161,"holding":0},{"time":21181,"holding":0},{"time":21199,"holding":0},{"time":21280,"holding":0},{"time":21358,"holding":0},{"time":21397,"holding":0},{"time":21440,"holding":0},{"time":21585,"holding":0},{"time":21659,"holding":0},{"time":21699,"holding":0},{"time":21798,"holding":0},{"time":21921,"holding":0},{"time":22122,"holding":63},{"time":22246,"holding":0},{"time":22284,"holding":0},{"time":22563,"holding":0},{"time":22602,"holding":0},{"time":22715,"holding":0},{"time":22796,"holding":0},{"time":22877,"holding":0},{"time":22914,"holding":0},{"time":23035,"holding":0},{"time":23074,"holding":0},{"time":23186,"holding":0},{"time":23236,"holding":0},{"time":23702,"holding":0},{"time":23964,"holding":0},{"time":23998,"holding":0},{"time":24175,"holding":0},{"time":24220,"holding":0},{"time":24340,"holding":0},{"time":24382,"holding":0},{"time":24466,"holding":0},{"time":24635,"holding":0},{"time":24930,"holding":0},{"time":24970,"holding":0},{"time":25013,"holding":0},{"time":25057,"holding":0},{"time":25133,"holding":0},{"time":25245,"holding":0},{"time":25275,"holding":0},{"time":25394,"holding":0},{"time":25482,"holding":0},{"time":25600,"holding":0},{"time":25656,"holding":0},{"time":25684,"holding":0},{"time":25740,"holding":0},{"time":25800,"holding":0},{"time":25842,"holding":0},{"time":25887,"holding":0},{"time":25928,"holding":0},{"time":25972,"holding":0},{"time":26017,"holding":0},{"time":26104,"holding":0},{"time":26151,"holding":0},{"time":26195,"holding":0},{"time":26238,"holding":0},{"time":26287,"holding":0},{"time":26309,"holding":0},{"time":26407,"holding":0},{"time":26495,"holding":0},{"time":26585,"holding":0},{"time":26674,"holding":0},{"time":26899,"holding":0},{"time":26933,"holding":171},{"time":27271,"holding":177},{"time":27543,"holding":0},{"time":27591,"holding":0},{"time":27615,"holding":93},{"time":27793,"holding":97},{"time":28002,"holding":0},{"time":28118,"holding":0},{"time":28147,"holding":0},{"time":28202,"holding":0},{"time":28262,"holding":0},{"time":28351,"holding":0},{"time":28465,"holding":0},{"time":28523,"holding":0},{"time":28551,"holding":0},{"time":28634,"holding":0},{"time":28677,"holding":0},{"time":28734,"holding":0},{"time":28790,"holding":0},{"time":28858,"holding":0},{"time":28888,"holding":0},{"time":28915,"holding":0},{"time":28958,"holding":0},{"time":28985,"holding":0},{"time":29035,"holding":0},{"time":29057,"holding":0},{"time":29084,"holding":0},{"time":29131,"holding":0},{"time":29154,"holding":0},{"time":29202,"holding":0},{"time":29230,"holding":0},{"time":29264,"holding":0},{"time":29290,"holding":0},{"time":29319,"holding":0},{"time":29383,"holding":0},{"time":29414,"holding":0},{"time":29452,"holding":0},{"time":29483,"holding":0},{"time":29518,"holding":0},{"time":29577,"holding":0},{"time":29614,"holding":0},{"time":29781,"holding":0},{"time":29906,"holding":113},{"time":30054,"holding":0},{"time":30220,"holding":0},{"time":30566,"holding":89},{"time":30723,"holding":0},{"time":30787,"holding":0},{"time":30812,"holding":88},{"time":31326,"holding":177},{"time":31978,"holding":0},{"time":32016,"holding":0},{"time":32157,"holding":0},{"time":32198,"holding":0},{"time":32366,"holding":226},{"time":32955,"holding":0},{"time":33077,"holding":0},{"time":33115,"holding":0},{"time":33193,"holding":0},{"time":33412,"holding":0},{"time":33496,"holding":0},{"time":33819,"holding":0},{"time":34045,"holding":0},{"time":34092,"holding":0},{"time":34647,"holding":0},{"time":35064,"holding":559}],"right_keys":[{"time":1797,"holding":0},{"time":1983,"holding":0},{"time":2160,"holding":282},{"time":2529,"holding":0},{"time":2739,"holding":0},{"time":2823,"holding":0},{"time":2865,"holding":0},{"time":2991,"holding":0},{"time":3075,"holding":0},{"time":3327,"holding":0},{"time":3537,"holding":0},{"time":3873,"holding":0},{"time":4190,"holding":0},{"time":4278,"holding":0},{"time":5035,"holding":160},{"time":5208,"holding":0},{"time":5380,"holding":0},{"time":5551,"holding":0},{"time":5719,"holding":0},{"time":5887,"holding":0},{"time":6060,"holding":0},{"time":6233,"holding":0},{"time":6403,"holding":0},{"time":6569,"holding":0},{"time":6736,"holding":0},{"time":6907,"holding":0},{"time":7076,"holding":0},{"time":7204,"holding":0},{"time":7247,"holding":0},{"time":7413,"holding":0},{"time":7583,"holding":0},{"time":7752,"holding":0},{"time":7923,"holding":0},{"time":8053,"holding":0},{"time":8266,"holding":0},{"time":8392,"holding":0},{"time":8602,"holding":0},{"time":8693,"holding":0},{"time":8776,"holding":0},{"time":8902,"holding":0},{"time":9113,"holding":50},{"time":9284,"holding":0},{"time":9365,"holding":0},{"time":9534,"holding":0},{"time":9763,"holding":0},{"time":9783,"holding":0},{"time":9847,"holding":0},{"time":9867,"holding":0},{"time":9948,"holding":0},{"time":10035,"holding":0},{"time":10463,"holding":129},{"time":10624,"holding":0},{"time":10839,"holding":0},{"time":10921,"holding":0},{"time":11001,"holding":0},{"time":11087,"holding":0},{"time":11304,"holding":0},{"time":11473,"holding":0},{"time":11647,"holding":0},{"time":11818,"holding":0},{"time":11993,"holding":0},{"time":12161,"holding":0},{"time":12336,"holding":0},{"time":12507,"holding":0},{"time":12673,"holding":0},{"time":12838,"holding":0},{"time":13010,"holding":0},{"time":13134,"holding":0},{"time":13178,"holding":0},{"time":13347,"holding":0},{"time":13517,"holding":0},{"time":13684,"holding":0},{"time":13858,"holding":0},{"time":13982,"holding":0},{"time":14066,"holding":0},{"time":14321,"holding":0},{"time":14530,"holding":0},{"time":14617,"holding":0},{"time":14705,"holding":0},{"time":14830,"holding":0},{"time":15044,"holding":0},{"time":15214,"holding":0},{"time":15303,"holding":0},{"time":15463,"holding":0},{"time":15548,"holding":0},{"time":15610,"holding":0},{"time":15632,"holding":0},{"time":15694,"holding":0},{"time":15717,"holding":0},{"time":15781,"holding":0},{"time":15804,"holding":0},{"time":15969,"holding":66},{"time":16054,"holding":135},{"time":16253,"holding":145},{"time":16460,"holding":0},{"time":16567,"holding":171},{"time":16817,"holding":67},{"time":16903,"holding":0},{"time":16934,"holding":0},{"time":17056,"holding":0},{"time":17391,"holding":0},{"time":17440,"holding":0},{"time":17557,"holding":154},{"time":17738,"holding":0},{"time":17825,"holding":0},{"time":17911,"holding":0},{"time":17933,"holding":138},{"time":18187,"holding":87},{"time":18371,"holding":0},{"time":18400,"holding":0},{"time":18429,"holding":85},{"time":18583,"holding":0},{"time":18637,"holding":0},{"time":18679,"holding":0},{"time":18723,"holding":0},{"time":18768,"holding":0},{"time":18807,"holding":0},{"time":18848,"holding":0},{"time":18891,"holding":0},{"time":18935,"holding":0},{"time":19100,"holding":0},{"time":19264,"holding":0},{"time":19344,"holding":0},{"time":19501,"holding":0},{"time":19662,"holding":0},{"time":19697,"holding":0},{"time":19744,"holding":0},{"time":19763,"holding":0},{"time":19780,"holding":0},{"time":19800,"holding":0},{"time":19901,"holding":0},{"time":20310,"holding":0},{"time":20586,"holding":0},{"time":20755,"holding":0},{"time":20922,"holding":0},{"time":20963,"holding":0},{"time":20984,"holding":0},{"time":21000,"holding":0},{"time":21040,"holding":0},{"time":21081,"holding":0},{"time":21100,"holding":0},{"time":21118,"holding":0},{"time":21238,"holding":0},{"time":21319,"holding":0},{"time":21625,"holding":0},{"time":21839,"holding":0},{"time":21882,"holding":0},{"time":22266,"holding":0},{"time":22583,"holding":0},{"time":22757,"holding":0},{"time":22897,"holding":0},{"time":23055,"holding":0},{"time":23216,"holding":0},{"time":23543,"holding":0},{"time":23622,"holding":0},{"time":23983,"holding":0},{"time":24097,"holding":0},{"time":24152,"holding":0},{"time":24263,"holding":0},{"time":24300,"holding":0},{"time":24340,"holding":0},{"time":24382,"holding":0},{"time":24422,"holding":0},{"time":24594,"holding":0},{"time":24761,"holding":0},{"time":24803,"holding":0},{"time":24849,"holding":0},{"time":24887,"holding":0},{"time":24930,"holding":0},{"time":24970,"holding":0},{"time":25013,"holding":0},{"time":25057,"holding":0},{"time":25102,"holding":0},{"time":25377,"holding":0},{"time":25452,"holding":0},{"time":25628,"holding":0},{"time":25726,"holding":0},{"time":26057,"holding":90},{"time":26271,"holding":0},{"time":26352,"holding":0},{"time":26453,"holding":0},{"time":26543,"holding":0},{"time":26630,"holding":0},{"time":26719,"holding":0},{"time":26760,"holding":0},{"time":26803,"holding":0},{"time":26863,"holding":0},{"time":27100,"holding":161},{"time":27445,"holding":86},{"time":27572,"holding":0},{"time":27971,"holding":0},{"time":28246,"holding":0},{"time":28323,"holding":0},{"time":28492,"holding":0},{"time":28693,"holding":0},{"time":28750,"holding":0},{"time":28808,"holding":0},{"time":28842,"holding":0},{"time":28942,"holding":0},{"time":29018,"holding":0},{"time":29112,"holding":0},{"time":29171,"holding":0},{"time":29351,"holding":0},{"time":29555,"holding":0},{"time":29636,"holding":0},{"time":29684,"holding":0},{"time":29748,"holding":0},{"time":30077,"holding":105},{"time":30239,"holding":89},{"time":30404,"holding":90},{"time":30557,"holding":0},{"time":30737,"holding":0},{"time":30800,"holding":0},{"time":30984,"holding":179},{"time":31305,"holding":0},{"time":31646,"holding":0},{"time":32017,"holding":0},{"time":32199,"holding":0},{"time":32323,"holding":0},{"time":32366,"holding":213},{"time":32600,"holding":359},{"time":33160,"holding":0},{"time":33232,"holding":0},{"time":33456,"holding":0},{"time":33530,"holding":0},{"time":33698,"holding":0},{"time":33740,"holding":0},{"time":33784,"holding":0},{"time":34006,"holding":0},{"time":34507,"holding":88},{"time":34609,"holding":0},{"time":34690,"holding":0},{"time":34780,"holding":0},{"time":34880,"holding":0},{"time":35069,"holding":555}],"end":35778,"sync":0,"bpm":[{"bpm":72,"starting_at":0},{"bpm":70,"starting_at":5300},{"bpm":141,"starting_at":8730},{"bpm":70,"starting_at":11580}]}